collective/person/__init__.py
collective/person/configure.zcml
collective/person/dependencies.zcml
collective/person/interfaces.py
collective/person/permissions.zcml
collective/person/profiles.zcml
collective/person/testing.py
collective/person/title_utilities.py
collective/person/utils.py
collective/person/behaviors/__init__.py
collective/person/behaviors/configure.zcml
collective/person/behaviors/person.py
collective/person/behaviors/user.py
collective/person/content/__init__.py
collective/person/content/person.py
collective/person/controlpanel/__init__.py
collective/person/controlpanel/configure.zcml
collective/person/controlpanel/controlpanel.py
collective/person/controlpanel/interfaces.py
collective/person/indexers/__init__.py
collective/person/indexers/configure.zcml
collective/person/indexers/person.py
collective/person/indexers/username.py
collective/person/locales/__init__.py
collective/person/locales/__main__.py
collective/person/locales/collective.person.pot
collective/person/locales/de/LC_MESSAGES/collective.person.po
collective/person/locales/es/LC_MESSAGES/collective.person.po
collective/person/locales/fi/LC_MESSAGES/collective.person.po
collective/person/locales/fr/LC_MESSAGES/collective.person.po
collective/person/locales/nl/LC_MESSAGES/collective.person.po
collective/person/locales/pt_BR/LC_MESSAGES/collective.person.po
collective/person/profiles/catalog/catalog.xml
collective/person/profiles/catalog/metadata.xml
collective/person/profiles/default/browserlayer.xml
collective/person/profiles/default/catalog.xml
collective/person/profiles/default/controlpanel.xml
collective/person/profiles/default/diff_tool.xml
collective/person/profiles/default/metadata.xml
collective/person/profiles/default/repositorytool.xml
collective/person/profiles/default/rolemap.xml
collective/person/profiles/default/types.xml
collective/person/profiles/default/registry/collective.person.controlpanel.interfaces.IPersonSettings.xml
collective_person-1.0.0b3.dist-info/METADATA
collective_person-1.0.0b3.dist-info/WHEEL
collective_person-1.0.0b3.dist-info/entry_points.txt
collective_person-1.0.0b3.dist-info/licenses/LICENSE.md
collective_person-1.0.0b3.dist-info/RECORD
