Metadata-Version: 2.4
Name: collective.person
Version: 1.0.0b3
Summary: A Person content type for Plone.
Project-URL: Changelog, https://github.com/collective/collective.person/blob/main/CHANGELOG.md
Project-URL: Homepage, https://github.com/collective/collective.person
Project-URL: Issues, https://github.com/collective/collective.person/issues
Project-URL: Repository, https://github.com/collective/collective.person/
Author-email: Érico Andrei <ericof@plone.org>
License: GNU General Public License v2 (GPLv2)
License-File: LICENSE.md
Keywords: Plone,Python
Classifier: Development Status :: 5 - Production/Stable
Classifier: Environment :: Web Environment
Classifier: Framework :: Plone
Classifier: Framework :: Plone :: 6.0
Classifier: Framework :: Plone :: 6.1
Classifier: Framework :: Plone :: Addon
Classifier: Framework :: Zope
Classifier: Framework :: Zope :: 5
Classifier: License :: OSI Approved :: GNU General Public License v2 (GPLv2)
Classifier: Programming Language :: Python
Classifier: Programming Language :: Python :: 3 :: Only
Classifier: Programming Language :: Python :: 3.10
Classifier: Programming Language :: Python :: 3.11
Classifier: Programming Language :: Python :: 3.12
Classifier: Programming Language :: Python :: 3.13
Requires-Python: >=3.10
Requires-Dist: collective-contact-behaviors>=1.0.0b5
Requires-Dist: plone-api
Requires-Dist: plone-exportimport
Requires-Dist: plone-restapi
Requires-Dist: plone-volto
Requires-Dist: products-cmfplone>=6.0.0
Provides-Extra: test
Requires-Dist: horse-with-no-namespace>=20250705.0; extra == 'test'
Requires-Dist: plone-app-testing; extra == 'test'
Requires-Dist: plone-restapi[test]; extra == 'test'
Requires-Dist: pytest-cov; extra == 'test'
Requires-Dist: pytest-plone>=1.0.0a1; extra == 'test'
Requires-Dist: zest-releaser[recommended]>=9.5.0; extra == 'test'
Requires-Dist: zestreleaser-towncrier>=1.3.0; extra == 'test'
